clynmut/__init__.py
clynmut/clynmut.py
clynmut/config.py
clynmut/utils.py
ClynMut-0.0.0.dist-info/LICENSE
ClynMut-0.0.0.dist-info/METADATA
ClynMut-0.0.0.dist-info/WHEEL
ClynMut-0.0.0.dist-info/top_level.txt
ClynMut-0.0.0.dist-info/RECORD
